repo_radar/__init__.py
repo_radar/audit_runner.py
repo_radar/audit_scripts/__init__.py
repo_radar/audit_scripts/run_config_audit.py
repo_radar/audit_scripts/run_llm_audit.py
repo_radar/config.py
repo_radar/examples/config.example.json
repo_radar/github_client.py
repo_radar/mcp_server.py
repo_radar/queries/__init__.py
repo_radar/queries/get_large_prs.py
repo_radar/queries/get_stale_or_long_lived_prs.py
repo_radar/queries.py
repo_radar/schema.py
repo_radar/schemas/__init__.py
repo_radar/schemas/tools.py
repo_radar/utils/__init__.py
repo_radar/utils/path_utils.py
repo_radar/utils/team_utils.py
repo_radar-0.1.1.dist-info/WHEEL
repo_radar-0.1.1.dist-info/entry_points.txt
repo_radar-0.1.1.dist-info/METADATA
repo_radar-0.1.1.dist-info/RECORD
