Metadata-Version: 2.3
Name: repo-radar
Version: 0.1.1
Summary: GitHub Pull Request audit toolkit with LLM and CLI support
Author: Karthick Shanmuga Rao
Author-email: Karthick Shanmuga Rao <karthikssfeb@gmail.com>
Requires-Dist: pygithub>=2.1.1
Requires-Dist: pydantic>=2.0
Requires-Dist: fastapi>=0.103.0
Requires-Dist: uvicorn>=0.23.0
Requires-Dist: python-dotenv>=1.0.0
Requires-Dist: tqdm>=4.67.1
Requires-Dist: openai>=1.97.1
Requires-Python: >=3.9
